MANIFEST.in
README.txt
setup.py
cfg/tipy.ini
databases/corp.db
databases/dict.db
databases/fb.db
databases/user.db
dictionaries/en_US.dic
stoplists/insanities_en.stoplist
tipy/__init__.py
tipy/char.py
tipy/clbk.py
tipy/cmbn.py
tipy/cntxt.py
tipy/db.py
tipy/drvr.py
tipy/gui.py
tipy/lg.py
tipy/main.py
tipy/minr.py
tipy/mrgr.py
tipy/prdct.py
tipy/slct.py
tipy/stngs.py
tipy/stpl.py
tipy/tknz.py
tipy.egg-info/PKG-INFO
tipy.egg-info/SOURCES.txt
tipy.egg-info/dependency_links.txt
tipy.egg-info/entry_points.txt
tipy.egg-info/requires.txt
tipy.egg-info/top_level.txt
txt/brown.txt
txt/fb.txt
txt/fr.txt