Metadata-Version: 1.1
Name: tipy
Version: 0.3.3
Summary: Text predictor.
Home-page: http://pypi.python.org/pypi/tipy/
Author: Mathieu Fourcroy
Author-email: mathieu.fourcroy@gmail.com
License: GPL
Keywords: text prediction competer keyboard
Platform: UNKNOWN
Classifier: Programming Language :: Python :: 3.4
Classifier: Topic :: Text Processing :: Linguistic
